setup.cfg
setup.py
unsplashdownloader/__init__.py
unsplashdownloader/crawl.py
unsplashdownloader.egg-info/PKG-INFO
unsplashdownloader.egg-info/SOURCES.txt
unsplashdownloader.egg-info/dependency_links.txt
unsplashdownloader.egg-info/entry_points.txt
unsplashdownloader.egg-info/requires.txt
unsplashdownloader.egg-info/top_level.txt