Metadata-Version: 1.1
Name: unsplashdownloader
Version: 1.1
Summary: Download all images from a user page or collection in unsplash
Home-page: https://github.com/reyreaud-l/unsplashdownloader
Author: Loic Reyreaud
Author-email: reyreaud.loic@gmail.com
License: UNKNOWN
Download-URL: https://github.com/reyreaud-l/unsplashdownloader/archive/1.1.tar.gz
Keywords: unsplash,downloader,wallpaper
Platform: UNKNOWN
